[
  {
    "id": 51073,
    "fen": "1Q6/8/8/8/8/2K5/k7/8 b - - 13 62",
    "lines": {
      "b8a7": "win",
      "b8a8": "win",
      "b8b3": "win"
    },
    "initialMove": {
      "san": "Ka3",
      "uci": "a2a3"
    }
  },
  {
    "id": 14588,
    "fen": "r1bqkbnr/p1pppppp/1pn5/8/2B5/4PQ2/PPPP1PPP/RNB1K1NR b KQkq - 3 3",
    "lines": {
      "c4f7": "win",
      "f3f7": "win"
    },
    "initialMove": {
      "san": "Bb7",
      "uci": "c8b7"
    }
  },
  {
    "id": 45815,
    "fen": "4k3/P2R4/2P2K2/8/8/8/8/8 b - - 16 79",
    "lines": {
      "d7d8": "win",
      "a7a8q": "win",
      "a7a8r": "win"
    },
    "initialMove": {
      "san": "Kf8",
      "uci": "e8f8"
    }
  },
  {
    "id": 30483,
    "fen": "8/3r4/1k6/3R4/1P2P3/5P2/3bK3/8 b - - 8 54",
    "lines": {
      "d5d7": {
        "b6c6": "win"
      }
    },
    "initialMove": {
      "san": "Bxb4",
      "uci": "d2b4"
    }
  },
  {
    "id": 32643,
    "fen": "3n2k1/2b1K1Pp/8/8/8/r7/8/5q2 b - - 1 53",
    "lines": {
      "g7f8q": "win"
    },
    "initialMove": {
      "san": "Qf8+",
      "uci": "f1f8"
    }
  },
  {
    "id": 2341,
    "fen": "rnbqkb1r/ppp2ppp/4pn2/1N1p4/3P1B2/8/PPP1PPPP/R2QKBNR b KQkq - 1 4",
    "lines": {
      "b5c7": {
        "e8d7": {
          "c7a8": {
            "f8d6": "win"
          }
        }
      }
    },
    "initialMove": {
      "san": "c6",
      "uci": "c7c6"
    }
  },
  {
    "id": 32396,
    "fen": "8/8/1p4p1/pB1K2k1/P7/7r/8/8 b - - 1 56",
    "lines": {
      "b5d7": {
        "f5f4": {
          "d7h3": {
            "f4g3": "win"
          }
        }
      }
    },
    "initialMove": {
      "san": "Kf5",
      "uci": "g5f5"
    }
  },
  {
    "id": 27516,
    "fen": "8/7P/8/1p6/8/1Pbk1K2/4p3/1R6 b - - 1 42",
    "lines": {
      "b1e1": {
        "c3f6": "win"
      }
    },
    "initialMove": {
      "san": "e1=Q",
      "uci": "e2e1q"
    }
  },
  {
    "id": 59837,
    "fen": "6k1/3n2P1/6KP/8/8/2B5/8/8 b - - 10 84",
    "lines": {
      "h6h7": "win"
    },
    "initialMove": {
      "san": "Nb6",
      "uci": "d7b6"
    }
  },
  {
    "id": 35622,
    "fen": "2N5/5k2/5p2/6pp/4b2P/6K1/8/8 b - - 3 37",
    "lines": {
      "c8d6": {
        "f7e6": {
          "d6e4": {
            "e6f5": "win"
          }
        }
      }
    },
    "initialMove": {
      "san": "g4",
      "uci": "g5g4"
    }
  },
  {
    "id": 26339,
    "fen": "8/8/6R1/p6p/r5kP/8/6PK/8 b - - 9 48",
    "lines": {
      "g2g3": "win"
    },
    "initialMove": {
      "san": "Kxh4",
      "uci": "g4h4"
    }
  },
  {
    "id": 25300,
    "fen": "8/8/pp1k4/5N2/PP6/1K6/6r1/8 b - - 7 44",
    "lines": {
      "f5e3": {
        "d5e4": {
          "e3g2": {
            "e4d4": "win"
          }
        }
      }
    },
    "initialMove": {
      "san": "Kd5",
      "uci": "d6d5"
    }
  },
  {
    "id": 51101,
    "fen": "8/8/8/8/8/5K2/1R6/6k1 b - - 99 113",
    "lines": {
      "b2b1": "win"
    },
    "initialMove": {
      "san": "Kf1",
      "uci": "g1f1"
    }
  },
  {
    "id": 3622,
    "fen": "8/5r2/6N1/5pKP/5P2/6k1/8/8 b - - 0 79",
    "lines": {
      "g6e5": {
        "f3e4": {
          "e5f7": {
            "e4d5": "win"
          }
        }
      }
    },
    "initialMove": {
      "san": "Kf3",
      "uci": "g3f3"
    }
  },
  {
    "id": 46410,
    "fen": "6k1/5R2/6K1/1r4PN/1p6/8/8/8 b - - 3 57",
    "lines": {
      "h5f6": {
        "g8h8": {
          "f7f8": "win",
          "f7h7": "win"
        }
      }
    },
    "initialMove": {
      "san": "b3",
      "uci": "b4b3"
    }
  },
  {
    "id": 36906,
    "fen": "8/8/P7/1K4p1/4r1P1/8/8/5k2 b - - 0 47",
    "lines": {
      "a6a7": {
        "g4f4": {
          "a7a8q": {
            "g5g4": "win"
          }
        }
      }
    },
    "initialMove": {
      "san": "Rxg4",
      "uci": "e4g4"
    }
  },
  {
    "id": 34762,
    "fen": "8/8/8/4p1B1/4k3/r3N3/5K2/8 b - - 1 52",
    "lines": {
      "e3c2": {
        "d4d5": {
          "c2a3": {
            "d5c5": "win"
          }
        }
      }
    },
    "initialMove": {
      "san": "Kd4",
      "uci": "e4d4"
    }
  },
  {
    "id": 26143,
    "fen": "6k1/5Q2/8/6N1/8/4KP2/P7/8 b - - 44 93",
    "lines": {
      "f7f8": "win",
      "f7h7": "win"
    },
    "initialMove": {
      "san": "Kh8",
      "uci": "g8h8"
    }
  },
  {
    "id": 44918,
    "fen": "8/8/6Q1/p7/1n2k3/8/4K3/2q5 b - - 17 66",
    "lines": {
      "g6h6": {
        "f4f5": {
          "h6c1": {
            "b4d5": "win"
          }
        }
      }
    },
    "initialMove": {
      "san": "Kf4",
      "uci": "e4f4"
    }
  },
  {
    "id": 33692,
    "fen": "8/8/8/8/1K2N3/6Q1/6k1/8 b - - 8 57",
    "lines": {
      "g3f2": "win"
    },
    "initialMove": {
      "san": "Kf1",
      "uci": "g2f1"
    }
  }
]
