{
  "puzzle_data": {
    "initial_fen": "3rk2r/1p2qppp/p1np4/3Np2b/4Pn2/2P2N2/PPB2PPP/R2Q1RK1 b k - 9 15",
    "initial_move_san": "Qe6",
    "initial_move_uci": "e7e6",
    "puzzle_fen": "3rk2r/1p3ppp/p1npq3/3Np2b/4Pn2/2P2N2/PPB2PPP/R2Q1RK1 w k - 10 16",
    "lines": {
      "d5c7": {
        "e8f8": {
          "c7e6": {
            "f7e6": "win"
          }
        }
      }
    }
  },
  "metadata": {
    "id": 107005,
    "rating": 1102,
    "enabled": true,
    "color": "white",
    "game_id": "A2cXLclO",
    "attempts": 26,
    "vote": 1
  }
}