{
  "puzzle_data": {
    "initial_fen": "2r1r1k1/6p1/p2Q1n1p/1q6/N7/1P5P/5PP1/1R1R2K1 w - - 3 34",
    "initial_move_san": "Qd3",
    "initial_move_uci": "d6d3",
    "puzzle_fen": "2r1r1k1/6p1/p4n1p/1q6/N7/1P1Q3P/5PP1/1R1R2K1 b - - 4 34",
    "lines": {
      "e8e1": {
        "d1e1": {
          "b5d3": {
            "a4b6": "win"
          }
        }
      }
    }
  },
  "metadata": {
    "id": 108519,
    "rating": 1442,
    "enabled": true,
    "color": "black",
    "game_id": "UPacjwBH",
    "attempts": 341,
    "vote": 10
  }
}