{
  "puzzle_data": {
    "initial_fen": "r4r1k/1b3p2/p5qP/1pp5/2n1P3/2P5/PP4BQ/1K1R2NR w - - 0 28",
    "initial_move_san": "Qf4",
    "initial_move_uci": "h2f4",
    "puzzle_fen": "r4r1k/1b3p2/p5qP/1pp5/2n1PQ2/2P5/PP4B1/1K1R2NR b - - 1 28",
    "lines": {
      "g6g2": {
        "f4f6": {
          "h8h7": {
            "g1e2": "win"
          }
        }
      }
    }
  },
  "metadata": {
    "id": 111294,
    "rating": 1816,
    "enabled": true,
    "color": "black",
    "game_id": "LXaF5LWn",
    "attempts": 882,
    "vote": 27
  }
}