{
  "puzzle_data": {
    "initial_fen": "5rn1/1pq4k/p1nbbrpp/3pNp2/P1pP4/2P3N1/1P1B1PPP/RBQ1R1K1 b - - 7 25",
    "initial_move_san": "Nxe5",
    "initial_move_uci": "c6e5",
    "puzzle_fen": "5rn1/1pq4k/p2bbrpp/3pnp2/P1pP4/2P3N1/1P1B1PPP/RBQ1R1K1 w - - 0 26",
    "lines": {
      "d4e5": {
        "d6e5": {
          "e1e5": {
            "f8e8": "win"
          }
        }
      }
    }
  },
  "metadata": {
    "id": 112194,
    "rating": 1826,
    "enabled": true,
    "color": "white",
    "game_id": "0bGBugYW",
    "attempts": 707,
    "vote": 18
  }
}