{
  "puzzle_data": {
    "initial_fen": "3b2k1/p1pR1pp1/1pn2q1p/3Qp3/P3P3/2P2P2/1P3PKP/8 b - - 3 22",
    "initial_move_san": "Qe6",
    "initial_move_uci": "f6e6",
    "puzzle_fen": "3b2k1/p1pR1pp1/1pn1q2p/3Qp3/P3P3/2P2P2/1P3PKP/8 w - - 4 23",
    "lines": {
      "d5e6": {
        "f7e6": {
          "b2b4": {
            "g8f8": {
              "b4b5": {
                "c6a5": {
                  "d7d8": {
                    "f8e7": "win"
                  }
                }
              }
            }
          }
        }
      }
    }
  },
  "metadata": {
    "id": 113858,
    "rating": 2758,
    "enabled": true,
    "color": "white",
    "game_id": "WCa0Oypf",
    "attempts": 431,
    "vote": 7
  }
}