{
  "puzzle_data": {
    "initial_fen": "2r3k1/5ppp/5q2/8/3p4/1Q2pP2/P3P1PP/R3KB2 w - - 0 28",
    "initial_move_san": "Rb1",
    "initial_move_uci": "a1b1",
    "puzzle_fen": "2r3k1/5ppp/5q2/8/3p4/1Q2pP2/P3P1PP/1R2KB2 b - - 1 28",
    "lines": {
      "f6h4": {
        "e1d1": {
          "h4f2": {
            "b3b4": {
              "f2f1": {
                "b4e1": {
                  "f1g2": {
                    "b1c1": "win"
                  }
                }
              }
            }
          }
        }
      }
    }
  },
  "metadata": {
    "id": 11617,
    "rating": 1651,
    "enabled": true,
    "color": "black",
    "game_id": "jqb7pu2k",
    "attempts": 744,
    "vote": -1
  }
}