{
  "puzzle_data": {
    "initial_fen": "8/8/R6p/1N1np1k1/2r5/2P4P/2P2PK1/8 w - - 5 44",
    "initial_move_san": "Re6",
    "initial_move_uci": "a6e6",
    "puzzle_fen": "8/8/4R2p/1N1np1k1/2r5/2P4P/2P2PK1/8 b - - 6 44",
    "lines": {
      "d5f4": {
        "g2f1": {
          "f4e6": {
            "b5d6": "win"
          }
        }
      }
    }
  },
  "metadata": {
    "id": 118104,
    "rating": 1341,
    "enabled": true,
    "color": "black",
    "game_id": "WvaNoWCg",
    "attempts": 78,
    "vote": 4
  }
}