{
  "puzzle_data": {
    "initial_fen": "r1q1kbnr/p3ppp1/2pp4/8/4P2p/4B1Pb/PPPN1PBP/R2Q1RK1 w kq - 0 11",
    "initial_move_san": "Qf3",
    "initial_move_uci": "d1f3",
    "puzzle_fen": "r1q1kbnr/p3ppp1/2pp4/8/4P2p/4BQPb/PPPN1PBP/R4RK1 b kq - 1 11",
    "lines": {
      "h3g4": {
        "g2h3": {
          "g4h3": {
            "f1e1": "win"
          }
        }
      }
    }
  },
  "metadata": {
    "id": 119687,
    "rating": 1973,
    "enabled": true,
    "color": "black",
    "game_id": "cIPDOOGz",
    "attempts": 793,
    "vote": 28
  }
}