{
  "puzzle_data": {
    "initial_fen": "rnbqkb1r/1pp2ppp/p3pn2/3P4/4P3/2N2N2/PP3PPP/R1BQKB1R b KQkq - 1 7",
    "initial_move_san": "Bb4",
    "initial_move_uci": "f8b4",
    "puzzle_fen": "rnbqk2r/1pp2ppp/p3pn2/3P4/1b2P3/2N2N2/PP3PPP/R1BQKB1R w KQkq - 2 8",
    "lines": {
      "d1a4": {
        "c7c6": {
          "a4b4": {
            "c6d5": "win"
          }
        }
      }
    }
  },
  "metadata": {
    "id": 120019,
    "rating": 1531,
    "enabled": true,
    "color": "white",
    "game_id": "1ca0zvDI",
    "attempts": 190,
    "vote": 5
  }
}