{
  "puzzle_data": {
    "initial_fen": "r7/p2q1rnk/1p2Nnpp/2pP1p2/2P1pP1P/2Q1P1PR/P2N2K1/7R w - - 7 29",
    "initial_move_san": "Ng5+",
    "initial_move_uci": "e6g5",
    "puzzle_fen": "r7/p2q1rnk/1p3npp/2pP1pN1/2P1pP1P/2Q1P1PR/P2N2K1/7R b - - 8 29",
    "lines": {
      "h6g5": {
        "h4g5": {
          "f6h5": {
            "h3h4": "win"
          }
        }
      }
    }
  },
  "metadata": {
    "id": 121017,
    "rating": 1832,
    "enabled": true,
    "color": "black",
    "game_id": "htrZGSRC",
    "attempts": 542,
    "vote": 13
  }
}