{
  "puzzle_data": {
    "initial_fen": "8/2k5/2p5/1p2p1P1/1P1nN1r1/3K1p2/8/5R2 b - - 4 38",
    "initial_move_san": "Kd7",
    "initial_move_uci": "c7d7",
    "puzzle_fen": "8/3k4/2p5/1p2p1P1/1P1nN1r1/3K1p2/8/5R2 w - - 5 39",
    "lines": {
      "e4f6": {
        "d7e6": {
          "f6g4": {
            "c6c5": "win"
          }
        }
      }
    }
  },
  "metadata": {
    "id": 121335,
    "rating": 1341,
    "enabled": true,
    "color": "white",
    "game_id": "QU0qpVki",
    "attempts": 16,
    "vote": 1
  }
}