{
  "puzzle_data": {
    "initial_fen": "3r4/p1p2ppp/Qpk5/8/1qP5/3bB3/5PPP/2R3K1 b - - 2 25",
    "initial_move_san": "Bxc4",
    "initial_move_uci": "d3c4",
    "puzzle_fen": "3r4/p1p2ppp/Qpk5/8/1qb5/4B3/5PPP/2R3K1 w - - 0 26",
    "lines": {
      "c1c4": {
        "b4c4": {
          "a6c4": {
            "c6b7": "win"
          }
        }
      }
    }
  },
  "metadata": {
    "id": 1550,
    "rating": 1254,
    "enabled": true,
    "color": "white",
    "game_id": "m4JVnfnz",
    "attempts": 56,
    "vote": 0
  }
}