{
  "puzzle_data": {
    "initial_fen": "r1b1kb1r/p1q2ppp/1n2p1n1/1P1pP3/2pP4/N4N2/PPQ1BPPP/R1B1K2R w KQkq - 0 11",
    "initial_move_san": "Bf4",
    "initial_move_uci": "c1f4",
    "puzzle_fen": "r1b1kb1r/p1q2ppp/1n2p1n1/1P1pP3/2pP1B2/N4N2/PPQ1BPPP/R3K2R b KQkq - 1 11",
    "lines": {
      "g6f4": {
        "e1g1": "win"
      }
    }
  },
  "metadata": {
    "id": 16384,
    "rating": 1046,
    "enabled": true,
    "color": "black",
    "game_id": "u35912d7",
    "attempts": 44,
    "vote": 0
  }
}