{
  "puzzle_data": {
    "initial_fen": "8/8/Q2bk2p/1p1p1b1P/1P6/PK2P3/2r5/8 b - - 8 50",
    "initial_move_san": "Rd2",
    "initial_move_uci": "c2d2",
    "puzzle_fen": "8/8/Q2bk2p/1p1p1b1P/1P6/PK2P3/3r4/8 w - - 9 51",
    "lines": {
      "a6c8": {
        "e6e7": {
          "c8f5": {
            "d2g2": "win"
          }
        }
      }
    }
  },
  "metadata": {
    "id": 16806,
    "rating": 1318,
    "enabled": true,
    "color": "white",
    "game_id": "ow36yk1i",
    "attempts": 23,
    "vote": -1
  }
}