{
  "puzzle_data": {
    "initial_fen": "r1b2rk1/ppp2pp1/2nq3p/2b1p3/2P5/3P1N2/PP2BPPP/R1BQK2R w KQ - 1 11",
    "initial_move_san": "Nh4",
    "initial_move_uci": "f3h4",
    "puzzle_fen": "r1b2rk1/ppp2pp1/2nq3p/2b1p3/2P4N/3P4/PP2BPPP/R1BQK2R b KQ - 2 11",
    "lines": {
      "d6d4": {
        "c1e3": {
          "c5b4": {
            "e3d2": {
              "b4d2": {
                "d1d2": {
                  "d4h4": {
                    "e1g1": "win"
                  }
                }
              },
              "d4h4": {
                "d2b4": {
                  "c6b4": {
                    "a2a3": {
                      "b4c6": {
                        "e2f3": "win"
                      }
                    }
                  }
                }
              }
            }
          }
        }
      }
    }
  },
  "metadata": {
    "id": 2634,
    "rating": 2067,
    "enabled": true,
    "color": "black",
    "game_id": "yphksg0d",
    "attempts": 37961,
    "vote": 541
  }
}