{
  "puzzle_data": {
    "initial_fen": "3r1k2/5ppQ/5r2/pq4N1/1n6/1P2N3/5PPP/4R1K1 b - - 4 27",
    "initial_move_san": "Rdd6",
    "initial_move_uci": "d8d6",
    "puzzle_fen": "5k2/5ppQ/3r1r2/pq4N1/1n6/1P2N3/5PPP/4R1K1 w - - 5 28",
    "lines": {
      "e3f5": {
        "b5f1": {
          "g1f1": {
            "a5a4": {
              "h7g7": "win",
              "h7h8": "win"
            }
          }
        }
      },
      "h7h8": {
        "f8e7": {
          "e3d5": {
            "e7d7": {
              "h8e8": "win"
            }
          }
        }
      }
    }
  },
  "metadata": {
    "id": 30198,
    "rating": 1584,
    "enabled": true,
    "color": "white",
    "game_id": "9f872m5q",
    "attempts": 1918,
    "vote": 51
  }
}