{
  "puzzle_data": {
    "initial_fen": "r5k1/pp3p1p/2p3p1/8/P1Pqr3/3P1Q1P/R1P2bP1/1N1K1R2 b - - 1 23",
    "initial_move_san": "Bh4",
    "initial_move_uci": "f2h4",
    "puzzle_fen": "r5k1/pp3p1p/2p3p1/8/P1Pqr2b/3P1Q1P/R1P3P1/1N1K1R2 w - - 2 24",
    "lines": {
      "f3e4": {
        "d4e4": {
          "d3e4": {
            "a8e8": "win"
          }
        }
      }
    }
  },
  "metadata": {
    "id": 37144,
    "rating": 1758,
    "enabled": true,
    "color": "white",
    "game_id": "indakd1o",
    "attempts": 5038,
    "vote": 38
  }
}