{
  "puzzle_data": {
    "initial_fen": "r3k2N/pp2q1pp/2p5/3P4/Q1Bpn1b1/8/PP1P1KPP/RNB4R w q - 1 13",
    "initial_move_san": "Kf1",
    "initial_move_uci": "f2f1",
    "puzzle_fen": "r3k2N/pp2q1pp/2p5/3P4/Q1Bpn1b1/8/PP1P2PP/RNB2K1R b q - 2 13",
    "lines": {
      "e7f6": {
        "f1e1": {
          "f6f2": "win"
        }
      },
      "e7f8": "retry",
      "e7h4": "retry"
    }
  },
  "metadata": {
    "id": 41934,
    "rating": 1335,
    "enabled": true,
    "color": "black",
    "game_id": "YM5VxZb3",
    "attempts": 95,
    "vote": 2
  }
}