{
  "puzzle_data": {
    "initial_fen": "rnb1kbnr/pppp1p1p/8/4q3/2B2p2/5Q2/PPPP2PP/RNB2RK1 w kq - 0 8",
    "initial_move_san": "Bxf7+",
    "initial_move_uci": "c4f7",
    "puzzle_fen": "rnb1kbnr/pppp1B1p/8/4q3/5p2/5Q2/PPPP2PP/RNB2RK1 b kq - 0 8",
    "lines": {
      "e8f7": {
        "d2d4": {
          "e5f5": {
            "c1f4": "win"
          }
        }
      }
    }
  },
  "metadata": {
    "id": 4292,
    "rating": 2403,
    "enabled": true,
    "color": "black",
    "game_id": "kcvezkxw",
    "attempts": 282,
    "vote": -13
  }
}