{
  "puzzle_data": {
    "initial_fen": "8/4k3/4Pp1p/p5p1/r1p5/2K3P1/4R3/8 b - - 1 44",
    "initial_move_san": "Kd6",
    "initial_move_uci": "e7d6",
    "puzzle_fen": "8/8/3kPp1p/p5p1/r1p5/2K3P1/4R3/8 w - - 2 45",
    "lines": {
      "e6e7": {
        "a4a2": {
          "e7e8n": {
            "d6c5": "win"
          }
        }
      }
    }
  },
  "metadata": {
    "id": 45993,
    "rating": 1158,
    "enabled": true,
    "color": "white",
    "game_id": "znpkqagu",
    "attempts": 1156,
    "vote": 4
  }
}