{
  "puzzle_data": {
    "initial_fen": "r3k2r/p4p1p/5P1b/2R5/b2p4/3N1Q2/3q2PP/5RK1 b kq - 0 23",
    "initial_move_san": "Kd7",
    "initial_move_uci": "e8d7",
    "puzzle_fen": "r6r/p2k1p1p/5P1b/2R5/b2p4/3N1Q2/3q2PP/5RK1 w - - 1 24",
    "lines": {
      "d3e5": {
        "d7e8": {
          "f3a8": "win"
        }
      },
      "f3b7": {
        "d7e8": {
          "b7e7": "win"
        }
      },
      "f3d5": "retry",
      "f3f5": "retry"
    }
  },
  "metadata": {
    "id": 52138,
    "rating": 1481,
    "enabled": true,
    "color": "white",
    "game_id": "5oyinctj",
    "attempts": 39033,
    "vote": 71
  }
}