{
  "puzzle_data": {
    "initial_fen": "2Q5/P3k3/1R6/8/8/r7/5K2/8 b - - 22 84",
    "initial_move_san": "Ra2+",
    "initial_move_uci": "a3a2",
    "puzzle_fen": "2Q5/P3k3/1R6/8/8/8/r4K2/8 w - - 23 85",
    "lines": {
      "f2e1": {
        "a2a1": {
          "e1d2": {
            "a1a2": {
              "c8c2": {
                "a2c2": {
                  "d2c2": {
                    "e7d7": {
                      "b6a6": "retry",
                      "b6b1": "retry",
                      "b6b2": "retry",
                      "b6b3": "retry",
                      "b6b4": "retry",
                      "b6b5": "retry",
                      "b6b7": "retry",
                      "b6b8": "retry",
                      "b6f6": "retry",
                      "b6g6": "retry",
                      "b6h6": "retry",
                      "c2b1": "retry",
                      "c2b2": "retry",
                      "c2b3": "retry",
                      "c2c1": "retry",
                      "c2c3": "retry",
                      "c2d1": "retry",
                      "c2d2": "retry",
                      "c2d3": "retry",
                      "a7a8q": {
                        "d7e7": {
                          "a8a1": "retry",
                          "a8a2": "retry",
                          "a8a3": "retry",
                          "a8a4": "retry",
                          "a8a5": "retry",
                          "a8a6": "retry",
                          "a8a7": {
                            "e7f8": {
                              "b6b8": "win"
                            }
                          },
                          "a8b7": "retry",
                          "a8b8": "retry",
                          "a8c6": "retry",
                          "a8c8": "retry",
                          "a8d5": "retry",
                          "a8e4": "retry",
                          "a8f3": "retry",
                          "a8g2": "retry",
                          "a8g8": "retry",
                          "a8h1": "retry",
                          "a8h8": "retry",
                          "b6a6": "retry",
                          "b6b1": "retry",
                          "b6b2": "retry",
                          "b6b3": "retry",
                          "b6b4": "retry",
                          "b6b5": "retry",
                          "b6b7": "retry",
                          "b6b8": "retry",
                          "b6c6": "retry",
                          "b6g6": "retry",
                          "b6h6": "retry",
                          "c2b1": "retry",
                          "c2b2": "retry",
                          "c2b3": "retry",
                          "c2c1": "retry",
                          "c2c3": "retry",
                          "c2d1": "retry",
                          "c2d2": "retry",
                          "c2d3": "retry"
                        }
                      },
                      "a7a8r": "retry"
                    }
                  }
                }
              },
              "d2c1": "retry",
              "d2c3": "retry",
              "d2d1": "retry",
              "d2d3": "retry"
            }
          },
          "e1e2": "retry"
        }
      },
      "f2f1": "retry",
      "f2f3": "retry",
      "f2g1": "retry",
      "f2g3": "retry"
    }
  },
  "metadata": {
    "id": 52548,
    "rating": 2411,
    "enabled": true,
    "color": "white",
    "game_id": "d2UGbFYx",
    "attempts": 113,
    "vote": 0
  }
}