{
  "puzzle_data": {
    "initial_fen": "2Q5/1p3ppk/p1p4p/2Pb4/1P4P1/P4Pq1/1B2r1P1/5RK1 w - - 10 31",
    "initial_move_san": "Qf5+",
    "initial_move_uci": "c8f5",
    "puzzle_fen": "8/1p3ppk/p1p4p/2Pb1Q2/1P4P1/P4Pq1/1B2r1P1/5RK1 b - - 11 31",
    "lines": {
      "g7g6": {
        "f5f7": {
          "d5f7": {
            "f1f2": {
              "e2f2": {
                "a3a4": {
                  "g3g2": "win"
                }
              },
              "g3f2": {
                "g1h2": {
                  "f2g2": "win"
                }
              }
            }
          }
        }
      }
    }
  },
  "metadata": {
    "id": 58534,
    "rating": 1389,
    "enabled": true,
    "color": "black",
    "game_id": "mLWNfz3d",
    "attempts": 56,
    "vote": 0
  }
}