{
  "puzzle_data": {
    "initial_fen": "2kr4/ppp3pp/4p3/4P3/2q2R2/PnN1B3/1P2P3/RK1Q4 w - - 0 24",
    "initial_move_san": "Re4",
    "initial_move_uci": "f4e4",
    "puzzle_fen": "2kr4/ppp3pp/4p3/4P3/2q1R3/PnN1B3/1P2P3/RK1Q4 b - - 1 24",
    "lines": {
      "d8d1": {
        "b1c2": {
          "b3a1": {
            "c2d1": {
              "c4b3": {
                "d1e1": "win"
              }
            }
          }
        }
      }
    }
  },
  "metadata": {
    "id": 59318,
    "rating": 1652,
    "enabled": true,
    "color": "black",
    "game_id": "F4dJgQB3",
    "attempts": 1046,
    "vote": -5
  }
}