{
  "puzzle_data": {
    "initial_fen": "1r2k2r/2qp1p1p/p1b3p1/R1Q1Pp2/2P2P2/4B3/6PP/5R1K w k - 4 25",
    "initial_move_san": "Rxa6",
    "initial_move_uci": "a5a6",
    "puzzle_fen": "1r2k2r/2qp1p1p/R1b3p1/2Q1Pp2/2P2P2/4B3/6PP/5R1K b k - 0 25",
    "lines": {
      "c6g2": {
        "h1g2": {
          "c7b7": {
            "c5d5": {
              "b7a6": {
                "e3c5": "win"
              }
            }
          }
        }
      }
    }
  },
  "metadata": {
    "id": 62012,
    "rating": 1894,
    "enabled": true,
    "color": "black",
    "game_id": "4dUX96oH",
    "attempts": 132697,
    "vote": 1445
  }
}