{
  "puzzle_data": {
    "initial_fen": "2r5/p4ppk/3p3p/8/8/q1P1RQ1P/5PPK/8 b - - 1 32",
    "initial_move_san": "Qb3",
    "initial_move_uci": "a3b3",
    "puzzle_fen": "2r5/p4ppk/3p3p/8/8/1qP1RQ1P/5PPK/8 w - - 2 33",
    "lines": {
      "f3f5": {
        "g7g6": {
          "f5c8": {
            "h7g7": "win"
          }
        }
      }
    }
  },
  "metadata": {
    "id": 66523,
    "rating": 1029,
    "enabled": true,
    "color": "white",
    "game_id": "K8ckh6jP",
    "attempts": 2723,
    "vote": 34
  }
}