{
  "puzzle_data": {
    "initial_fen": "2b3k1/p1r2p2/1p3P1p/1Nr1P1p1/8/6P1/1q4BP/3RR1K1 b - - 1 29",
    "initial_move_san": "Rc1",
    "initial_move_uci": "c5c1",
    "puzzle_fen": "2b3k1/p1r2p2/1p3P1p/1N2P1p1/8/6P1/1q4BP/2rRR1K1 w - - 2 30",
    "lines": {
      "d1d8": {
        "g8h7": {
          "g2e4": {
            "c8f5": {
              "e4f5": "win"
            }
          }
        }
      }
    }
  },
  "metadata": {
    "id": 67106,
    "rating": 1761,
    "enabled": true,
    "color": "white",
    "game_id": "S7VouF9u",
    "attempts": 139123,
    "vote": 941
  }
}