{
  "puzzle_data": {
    "initial_fen": "rn1q1rk1/ppp1b1pp/3ppn2/6N1/3PPB2/2NQ4/PPP3PP/R4K1R b - - 5 11",
    "initial_move_san": "Ng4",
    "initial_move_uci": "f6g4",
    "puzzle_fen": "rn1q1rk1/ppp1b1pp/3pp3/6N1/3PPBn1/2NQ4/PPP3PP/R4K1R w - - 6 12",
    "lines": {
      "g5e6": {
        "d8c8": {
          "e6f8": {
            "c8f8": "win"
          }
        }
      }
    }
  },
  "metadata": {
    "id": 68567,
    "rating": 977,
    "enabled": true,
    "color": "white",
    "game_id": "BszXTDTT",
    "attempts": 1724,
    "vote": 12
  }
}