{
  "puzzle_data": {
    "initial_fen": "r3r1k1/p3bppp/1p2b3/2p2q2/Q2pN3/P1PP4/1P1B1PPP/R3R1K1 b - - 3 17",
    "initial_move_san": "Bf6",
    "initial_move_uci": "e7f6",
    "puzzle_fen": "r3r1k1/p4ppp/1p2bb2/2p2q2/Q2pN3/P1PP4/1P1B1PPP/R3R1K1 w - - 4 18",
    "lines": {
      "e4d6": {
        "f5d3": {
          "d6e8": {
            "d3d2": "win"
          }
        }
      }
    }
  },
  "metadata": {
    "id": 74616,
    "rating": 1227,
    "enabled": true,
    "color": "white",
    "game_id": "TKDkj6g1",
    "attempts": 1877,
    "vote": 41
  }
}