{
  "puzzle_data": {
    "initial_fen": "r1bqr1k1/pp3ppp/2p5/2P5/1P1Pp3/P4N1P/1B1Q1KP1/R6R w - - 0 17",
    "initial_move_san": "Nh2",
    "initial_move_uci": "f3h2",
    "puzzle_fen": "r1bqr1k1/pp3ppp/2p5/2P5/1P1Pp3/P6P/1B1Q1KPN/R6R b - - 1 17",
    "lines": {
      "e4e3": {
        "d2e3": {
          "e8e3": {
            "f2e3": "win"
          }
        }
      }
    }
  },
  "metadata": {
    "id": 76659,
    "rating": 971,
    "enabled": true,
    "color": "black",
    "game_id": "MgDq4q5y",
    "attempts": 297,
    "vote": 14
  }
}