{
  "puzzle_data": {
    "initial_fen": "6r1/p2k3p/2p5/2Brpb2/1P3p2/3P4/P1P1RK1P/4R3 b - - 4 28",
    "initial_move_san": "Ke6",
    "initial_move_uci": "d7e6",
    "puzzle_fen": "6r1/p6p/2p1k3/2Brpb2/1P3p2/3P4/P1P1RK1P/4R3 w - - 5 29",
    "lines": {
      "c2c4": {
        "d5c5": {
          "b4c5": {
            "e5e4": "win"
          }
        }
      }
    }
  },
  "metadata": {
    "id": 76797,
    "rating": 1633,
    "enabled": true,
    "color": "white",
    "game_id": "Wpqn0yM5",
    "attempts": 17924,
    "vote": 140
  }
}