{
  "puzzle_data": {
    "initial_fen": "2b5/4n3/3N2p1/1pN1P2p/5K1P/k7/8/8 w - - 2 49",
    "initial_move_san": "Nxb5+",
    "initial_move_uci": "d6b5",
    "puzzle_fen": "2b5/4n3/6p1/1NN1P2p/5K1P/k7/8/8 b - - 0 49",
    "lines": {
      "a3b4": {
        "c5e4": {
          "b4b5": {
            "e4d6": "win"
          }
        }
      }
    }
  },
  "metadata": {
    "id": 76826,
    "rating": 823,
    "enabled": true,
    "color": "black",
    "game_id": "SMRH5DFi",
    "attempts": 130,
    "vote": 3
  }
}