{
  "puzzle_data": {
    "initial_fen": "4k1r1/pppr1p1p/5Q2/2q1pN2/4P3/2P2RP1/Pn5P/R6K b - - 1 21",
    "initial_move_san": "Rg6",
    "initial_move_uci": "g8g6",
    "puzzle_fen": "4k3/pppr1p1p/5Qr1/2q1pN2/4P3/2P2RP1/Pn5P/R6K w - - 2 22",
    "lines": {
      "f5g7": {
        "g6g7": {
          "f6g7": {
            "b2c4": "win"
          }
        }
      }
    }
  },
  "metadata": {
    "id": 79089,
    "rating": 1910,
    "enabled": true,
    "color": "white",
    "game_id": "fsVHmu65",
    "attempts": 7257,
    "vote": 170
  }
}