{
  "puzzle_data": {
    "initial_fen": "4r1k1/pp1b2bp/6q1/3p1p2/3PnQ2/1NPBB2P/PP6/R5K1 w - - 1 27",
    "initial_move_san": "Kh2",
    "initial_move_uci": "g1h2",
    "puzzle_fen": "4r1k1/pp1b2bp/6q1/3p1p2/3PnQ2/1NPBB2P/PP5K/R7 b - - 2 27",
    "lines": {
      "g7f8": {
        "a1g1": {
          "f8d6": {
            "g1g6": {
              "h7g6": {
                "f4d6": {
                  "e4d6": {
                    "e3f4": "win"
                  }
                }
              }
            }
          }
        }
      }
    }
  },
  "metadata": {
    "id": 80352,
    "rating": 2199,
    "enabled": true,
    "color": "black",
    "game_id": "VkZ4NN2S",
    "attempts": 3029,
    "vote": 34
  }
}