{
  "puzzle_data": {
    "initial_fen": "1r5r/4kp1p/p1p1bp2/b1N1p3/4P3/3R4/PPP1B1PP/2K4R b - - 5 17",
    "initial_move_san": "Bc4",
    "initial_move_uci": "e6c4",
    "puzzle_fen": "1r5r/4kp1p/p1p2p2/b1N1p3/2b1P3/3R4/PPP1B1PP/2K4R w - - 6 18",
    "lines": {
      "d3d7": {
        "e7e8": {
          "e2c4": {
            "h8f8": "win"
          }
        }
      }
    }
  },
  "metadata": {
    "id": 80933,
    "rating": 1003,
    "enabled": true,
    "color": "white",
    "game_id": "jvCTLKUj",
    "attempts": 107,
    "vote": 1
  }
}