{
  "puzzle_data": {
    "initial_fen": "r1b2rk1/1pqnb1pp/p3pp2/4P3/5Q2/2N2N2/PPB2PPP/R4RK1 w - - 0 15",
    "initial_move_san": "exf6",
    "initial_move_uci": "e5f6",
    "puzzle_fen": "r1b2rk1/1pqnb1pp/p3pP2/8/5Q2/2N2N2/PPB2PPP/R4RK1 b - - 0 15",
    "lines": {
      "c7f4": {
        "f6e7": {
          "f8e8": {
            "f1d1": "win"
          }
        }
      }
    }
  },
  "metadata": {
    "id": 81615,
    "rating": 1345,
    "enabled": true,
    "color": "black",
    "game_id": "H7eV6sw3",
    "attempts": 2342,
    "vote": 49
  }
}