{
  "puzzle_data": {
    "initial_fen": "1r1qk2r/2p2pp1/p1pp4/4p1bn/PP2P1b1/2NP2P1/2P2P1p/1RQ2R1K w k - 0 17",
    "initial_move_san": "Qa3",
    "initial_move_uci": "c1a3",
    "puzzle_fen": "1r1qk2r/2p2pp1/p1pp4/4p1bn/PP2P1b1/Q1NP2P1/2P2P1p/1R3R1K b k - 1 17",
    "lines": {
      "d8f6": "retry",
      "g4f3": {
        "h1h2": {
          "a6a5": "retry",
          "b8a8": "retry",
          "b8b4": "retry",
          "b8b5": "retry",
          "b8b6": "retry",
          "b8b7": "retry",
          "b8c8": "retry",
          "c6c5": "retry",
          "d6d5": "retry",
          "d8c8": "retry",
          "d8d7": "retry",
          "d8e7": "retry",
          "d8f6": "retry",
          "e8d7": "retry",
          "e8e7": "retry",
          "e8f8": "retry",
          "f7f5": "retry",
          "f7f6": "retry",
          "g5c1": "retry",
          "g5d2": "retry",
          "g5e7": "retry",
          "g5f4": "retry",
          "g5f6": "retry",
          "g7g6": "retry",
          "h5f4": {
            "h2g1": {
              "h8h1": "win"
            }
          },
          "h5f6": {
            "h2g1": {
              "h8h1": "win"
            }
          },
          "h5g3": "retry",
          "h8h6": "retry",
          "h8h7": "retry"
        }
      }
    }
  },
  "metadata": {
    "id": 856,
    "rating": 1557,
    "enabled": true,
    "color": "black",
    "game_id": "mfimhuoo",
    "attempts": 194786,
    "vote": 3088
  }
}