{
  "puzzle_data": {
    "initial_fen": "r5k1/ppbb2pp/4p1r1/P4p2/1P3P2/2P3R1/6BP/R1Bq1QK1 b - - 12 27",
    "initial_move_san": "Rxg3",
    "initial_move_uci": "g6g3",
    "puzzle_fen": "r5k1/ppbb2pp/4p3/P4p2/1P3P2/2P3r1/6BP/R1Bq1QK1 w - - 0 28",
    "lines": {
      "f1d1": {
        "g3g2": {
          "g1g2": {
            "d7b5": "win"
          }
        }
      }
    }
  },
  "metadata": {
    "id": 87738,
    "rating": 1399,
    "enabled": null,
    "color": "white",
    "game_id": "Wva2r0D1",
    "attempts": 1150,
    "vote": -45
  }
}