{
  "puzzle_data": {
    "initial_fen": "r1r3k1/pp3ppp/2p2q1n/4p2Q/4P3/2P1B1P1/P1P2P1P/R3R1K1 b - - 1 14",
    "initial_move_san": "Rd8",
    "initial_move_uci": "c8d8",
    "puzzle_fen": "r2r2k1/pp3ppp/2p2q1n/4p2Q/4P3/2P1B1P1/P1P2P1P/R3R1K1 w - - 2 15",
    "lines": {
      "e3g5": {
        "f6e6": {
          "g5d8": {
            "a8d8": "win"
          }
        }
      }
    }
  },
  "metadata": {
    "id": 88672,
    "rating": 1427,
    "enabled": true,
    "color": "white",
    "game_id": "qgCdY7zV",
    "attempts": 1515,
    "vote": 26
  }
}