{
  "puzzle_data": {
    "initial_fen": "1q5k/3PKQ2/6pp/8/8/7P/8/8 b - - 13 57",
    "initial_move_san": "Qe5+",
    "initial_move_uci": "b8e5",
    "puzzle_fen": "7k/3PKQ2/6pp/4q3/8/7P/8/8 w - - 14 58",
    "lines": {
      "f7e6": {
        "e5g7": {
          "e7e8": {
            "g7d4": {
              "d7d8q": {
                "d4d8": {
                  "e8d8": {
                    "h6h5": {
                      "d8c7": "retry",
                      "d8c8": "retry",
                      "d8d7": "retry",
                      "d8e7": {
                        "h8g7": {
                          "e6a2": "retry",
                          "e6a6": "retry",
                          "e6b3": "retry",
                          "e6b6": "retry",
                          "e6c4": "retry",
                          "e6c6": "retry",
                          "e6c8": "retry",
                          "e6d5": "retry",
                          "e6d6": "retry",
                          "e6d7": "retry",
                          "e6e1": "retry",
                          "e6e2": "retry",
                          "e6e3": "retry",
                          "e6e4": "retry",
                          "e6e5": "retry",
                          "e6f6": "retry",
                          "e6f7": {
                            "g7h6": {
                              "e7d6": "retry",
                              "e7d7": "retry",
                              "e7d8": "retry",
                              "e7e6": "retry",
                              "e7e8": "retry",
                              "e7f6": {
                                "h5h4": {
                                  "f7g6": "win"
                                }
                              },
                              "e7f8": "retry",
                              "f7a2": "retry",
                              "f7c4": "retry",
                              "f7d5": "retry",
                              "f7f1": "retry",
                              "f7f2": "retry",
                              "f7f3": "retry",
                              "f7f4": "retry",
                              "f7f6": "retry",
                              "f7f8": "retry",
                              "h3h4": "retry"
                            }
                          },
                          "e7d6": "retry",
                          "e7d7": "retry",
                          "e7e8": "retry",
                          "h3h4": "retry"
                        }
                      },
                      "d8e8": "retry",
                      "e6a6": "retry",
                      "e6b6": "retry",
                      "e6c4": "retry",
                      "e6c6": "retry",
                      "e6c8": "retry",
                      "e6d5": "retry",
                      "e6d6": "retry",
                      "e6e1": "retry",
                      "e6e2": "retry",
                      "e6e3": "retry",
                      "e6e4": "retry",
                      "e6e5": "retry",
                      "e6e7": "retry",
                      "e6e8": "retry",
                      "e6f6": "retry",
                      "e6f7": {
                        "h5h4": {
                          "d8c7": "retry",
                          "d8c8": "retry",
                          "d8d7": "retry",
                          "d8e7": {
                            "g6g5": {
                              "e7d6": "retry",
                              "e7d7": "retry",
                              "e7d8": "retry",
                              "e7e6": "retry",
                              "e7e8": "retry",
                              "e7f6": {
                                "g5g4": {
                                  "f7g7": "win"
                                }
                              },
                              "e7f8": {
                                "g5g4": {
                                  "f7g7": "win",
                                  "f7g8": "win",
                                  "f7h5": "win"
                                }
                              },
                              "f7a2": "retry",
                              "f7b3": "retry",
                              "f7c4": "retry",
                              "f7d5": "retry",
                              "f7e6": "retry",
                              "f7e8": "retry",
                              "f7f1": "retry",
                              "f7f2": "retry",
                              "f7f3": "retry",
                              "f7f5": "retry",
                              "f7f6": "retry",
                              "f7f8": "retry",
                              "f7g6": "retry",
                              "f7h5": "retry"
                            }
                          },
                          "d8e8": {
                            "g6g5": {
                              "e8d7": "retry",
                              "e8d8": "retry",
                              "e8e7": "retry",
                              "e8f8": {
                                "g5g4": {
                                  "f7g7": "win",
                                  "f7g8": "win",
                                  "f7h5": "win"
                                }
                              },
                              "f7a2": "retry",
                              "f7a7": "retry",
                              "f7b3": "retry",
                              "f7b7": "retry",
                              "f7c4": "retry",
                              "f7c7": "retry",
                              "f7d5": "retry",
                              "f7d7": "retry",
                              "f7e6": "retry",
                              "f7e7": "retry",
                              "f7f1": "retry",
                              "f7f2": "retry",
                              "f7f3": "retry",
                              "f7f5": "retry",
                              "f7f6": "retry",
                              "f7f8": "retry",
                              "f7g6": "retry",
                              "f7h5": "retry"
                            }
                          },
                          "f7a2": "retry",
                          "f7a7": "retry",
                          "f7b3": "retry",
                          "f7b7": "retry",
                          "f7c4": "retry",
                          "f7c7": "retry",
                          "f7d5": "retry",
                          "f7d7": "retry",
                          "f7e6": "retry",
                          "f7e7": "retry",
                          "f7e8": "retry",
                          "f7f1": "retry",
                          "f7f2": "retry",
                          "f7f3": "retry",
                          "f7f4": "retry",
                          "f7f6": "retry",
                          "f7f8": "retry"
                        }
                      },
                      "e6g6": "retry",
                      "h3h4": "retry"
                    }
                  }
                }
              }
            }
          }
        }
      }
    }
  },
  "metadata": {
    "id": 9164,
    "rating": 2210,
    "enabled": true,
    "color": "white",
    "game_id": "ncQwzhvS",
    "attempts": 1055,
    "vote": 0
  }
}