{
  "puzzle_data": {
    "initial_fen": "1r6/1P2k3/2r5/2P3R1/1B6/6P1/6K1/8 b - - 0 50",
    "initial_move_san": "Rxb7",
    "initial_move_uci": "b8b7",
    "puzzle_fen": "8/1r2k3/2r5/2P3R1/1B6/6P1/6K1/8 w - - 0 51",
    "lines": {
      "g5g7": {
        "e7e6": {
          "g7b7": {
            "c6c8": "win"
          }
        }
      }
    }
  },
  "metadata": {
    "id": 91843,
    "rating": 1018,
    "enabled": true,
    "color": "white",
    "game_id": "oHDQ8zpo",
    "attempts": 35,
    "vote": -1
  }
}