{
  "puzzle_data": {
    "initial_fen": "r3r1k1/ppq4p/2p1bpp1/3p1nP1/N4P2/P3PB2/1PP4Q/2K3RR w - - 0 23",
    "initial_move_san": "Qxh7+",
    "initial_move_uci": "h2h7",
    "puzzle_fen": "r3r1k1/ppq4Q/2p1bpp1/3p1nP1/N4P2/P3PB2/1PP5/2K3RR b - - 0 23",
    "lines": {
      "c7h7": {
        "h1h7": {
          "g8h7": {
            "a4c5": "win"
          }
        }
      }
    }
  },
  "metadata": {
    "id": 93071,
    "rating": 1537,
    "enabled": true,
    "color": "black",
    "game_id": "MZK3eIXH",
    "attempts": 677,
    "vote": 8
  }
}