{
  "puzzle_data": {
    "initial_fen": "3r2k1/1b1r1ppp/p3pb2/1p6/3N4/4PP1P/PP4PB/R2R2K1 w - - 3 22",
    "initial_move_san": "Rac1",
    "initial_move_uci": "a1c1",
    "puzzle_fen": "3r2k1/1b1r1ppp/p3pb2/1p6/3N4/4PP1P/PP4PB/2RR2K1 b - - 4 22",
    "lines": {
      "e6e5": {
        "h2e5": {
          "f6e5": {
            "g1f2": "win"
          }
        }
      }
    }
  },
  "metadata": {
    "id": 98944,
    "rating": 1541,
    "enabled": true,
    "color": "black",
    "game_id": "PLAzaR8a",
    "attempts": 1191,
    "vote": 32
  }
}